ocfl/__init__.py
ocfl/_version.py
ocfl/bagger.py
ocfl/command_line_utils.py
ocfl/constants.py
ocfl/digest.py
ocfl/inventory.py
ocfl/inventory_validator.py
ocfl/layout.py
ocfl/layout_0002_flat_direct.py
ocfl/layout_0003_hash_and_id_n_tuple.py
ocfl/layout_nnnn_flat_quoted.py
ocfl/layout_nnnn_tuple_tree.py
ocfl/layout_nnnn_uuid_quadtree.py
ocfl/layout_registry.py
ocfl/namaste.py
ocfl/new_version.py
ocfl/object.py
ocfl/object_utils.py
ocfl/pyfs.py
ocfl/storage_root.py
ocfl/validation_logger.py
ocfl/validator.py
ocfl/version_metadata.py
ocfl/w3c_datetime.py
ocfl/data/validation-errors.json
ocfl_py-2.0.2.data/scripts/ocfl-object.py
ocfl_py-2.0.2.data/scripts/ocfl-root.py
ocfl_py-2.0.2.data/scripts/ocfl-sidecar.py
ocfl_py-2.0.2.data/scripts/ocfl-validate.py
ocfl_py-2.0.2.dist-info/licenses/LICENSE.txt
ocfl_py-2.0.2.dist-info/METADATA
ocfl_py-2.0.2.dist-info/WHEEL
ocfl_py-2.0.2.dist-info/top_level.txt
ocfl_py-2.0.2.dist-info/RECORD
