Metadata-Version: 2.4
Name: ocfl-py
Version: 2.0.2
Summary: ocfl-py - A Python implementation of OCFL
Author-email: Simeon Warner <simeon.warner@cornell.edu>
Project-URL: Homepage, https://github.com/zimeon/ocfl-py
Classifier: Development Status :: 4 - Beta
Classifier: Intended Audience :: Developers
Classifier: Operating System :: OS Independent
Classifier: Programming Language :: Python
Classifier: Programming Language :: Python :: 3.8
Classifier: Programming Language :: Python :: 3.9
Classifier: Programming Language :: Python :: 3.10
Classifier: Programming Language :: Python :: 3.11
Classifier: Programming Language :: Python :: 3.12
Classifier: Programming Language :: Python :: 3.13
Classifier: Topic :: Internet :: WWW/HTTP
Classifier: Topic :: Software Development :: Libraries :: Python Modules
Requires-Python: >=3.8
License-File: LICENSE.txt
Requires-Dist: bagit>=1.8.1
Requires-Dist: dateutils>=0.6.6
Requires-Dist: fs>2.4.13
Requires-Dist: fs_s3fs>=1.1.1
Requires-Dist: pairtree>=0.8.1
Provides-Extra: testing
Requires-Dist: mock>=5.1; extra == "testing"
Requires-Dist: requests>=2.20.0; extra == "testing"
Dynamic: license-file
